COPYING
MANIFEST.in
README.rst
requirements.txt
setup.py
test_requirements.txt
djiki/__init__.py
djiki/forms.py
djiki/models.py
djiki/urls.py
djiki/utils.py
djiki/views.py
djiki.egg-info/PKG-INFO
djiki.egg-info/SOURCES.txt
djiki.egg-info/dependency_links.txt
djiki.egg-info/not-zip-safe
djiki.egg-info/top_level.txt
djiki/auth/__init__.py
djiki/auth/base.py
djiki/contrib/__init__.py
djiki/contrib/views.py
djiki/locale/ca/LC_MESSAGES/django.mo
djiki/locale/ca/LC_MESSAGES/django.po
djiki/locale/es/LC_MESSAGES/django.mo
djiki/locale/es/LC_MESSAGES/django.po
djiki/locale/pl/LC_MESSAGES/django.mo
djiki/locale/pl/LC_MESSAGES/django.po
djiki/locale/zh_CN/LC_MESSAGES/django.mo
djiki/locale/zh_CN/LC_MESSAGES/django.po
djiki/migrations/0001_initial.py
djiki/migrations/0002_add_language.py
djiki/migrations/__init__.py
djiki/parsers/__init__.py
djiki/parsers/html.py
djiki/parsers/raw.py
djiki/parsers/wikicreole.py
djiki/templates/djiki/base.html
djiki/templates/djiki/base_image.html
djiki/templates/djiki/base_page.html
djiki/templates/djiki/diff.html
djiki/templates/djiki/edit.html
djiki/templates/djiki/history.html
djiki/templates/djiki/image_edit.html
djiki/templates/djiki/image_history.html
djiki/templates/djiki/image_view.html
djiki/templates/djiki/latest_changes.html
djiki/templates/djiki/not_found.html
djiki/templates/djiki/view.html
djiki/templates/djiki/parser/image.html
djiki/templatetags/__init__.py
djiki/templatetags/djiki_tags.py
djiki/templating/__init__.py
djiki/templating/django_engine.py